gqlmod/__init__.py
gqlmod/_mod_impl.py
gqlmod/cli.py
gqlmod/importer.py
gqlmod/providers.py
gqlmod/helpers/__init__.py
gqlmod/helpers/aiohttp.py
gqlmod/helpers/debug.py
gqlmod/helpers/types.py
gqlmod/helpers/urllib.py
gqlmod/helpers/utils.py
gqlmod_starwars/__init__.py
gqlmod_starwars/data.py
gqlmod_starwars/schema.py
gqlmod-0.8.2.dist-info/LICENSE
gqlmod-0.8.2.dist-info/METADATA
gqlmod-0.8.2.dist-info/WHEEL
gqlmod-0.8.2.dist-info/entry_points.txt
gqlmod-0.8.2.dist-info/top_level.txt
gqlmod-0.8.2.dist-info/RECORD
