Metadata-Version: 2.1
Name: gqlmod
Version: 0.8.2
Summary: GraphQL Query Modules
Home-page: UNKNOWN
Author: Jamie Bliss
Author-email: jamie@ivyleav.es
License: LGPL
Project-URL: Tip Jar, https://ko-fi.com/astraluma
Project-URL: Source Code, https://github.com/gqlmod/gqlmod
Project-URL: Documentation, https://gqlmod.readthedocs.io/
Platform: UNKNOWN
Classifier: Programming Language :: Python :: 3
Classifier: Programming Language :: Python :: 3.7
Classifier: License :: OSI Approved :: GNU Lesser General Public License v3 or later (LGPLv3+)
Classifier: Operating System :: OS Independent
Requires-Python: >=3.7
Requires-Dist: graphql-core (>=3.1.0b2)
Requires-Dist: import-x
Requires-Dist: astor
Requires-Dist: setuptools
Requires-Dist: click
Provides-Extra: aiohttp
Requires-Dist: aiohttp ; extra == 'aiohttp'
